{"cameraMode":{"drawMode":0,"name":"Shaded","section":"Shading Mode"},"sceneLighting":true,"audioPlay":false,"sceneViewState":{"m_AlwaysRefresh":false,"showFog":true,"showSkybox":true,"showFlares":true,"showImageEffects":true,"showParticleSystems":true,"showVisualEffectGraphs":true,"m_FxEnabled":true},"in2DMode":false,"pivot":{"x":-20.355064392089845,"y":1.1637153625488282,"z":45.17229080200195},"rotation":{"x":-0.24084459245204926,"y":0.2507522702217102,"z":-0.0645546168088913,"w":-0.9354037642478943},"size":334.8022155761719,"orthographic":true}